Lab1/blackbox.v
module blackbox(b, g, r, t);
    output b;
    input  g, r, t;
    wire   w01, w02, w03, w04, w11, w23, w28, w35, w44, w45, w55, w80, w81, w86, w88, w89, w92, w94;
    and a54(b, w02, w04);
    or  o15(w02, w89, w28);
    and a97(w89, w45, w81);
    and a8(w28, w45, w01);
    not n90(w01, w81);
    or  o61(w04, w88, w92);
    not n79(w88, w92);
    and a77(w92, t, w86);
    or  o84(w86, w55, g);
    not n53(w55, r);
    and a72(w81, t, w80);
    or  o51(w80, r, w11);
    not n66(w11, g);
    or  o74(w45, w35, w94);
    and a50(w35, w44, g);
    not n99(w44, r);
    and a43(w94, r, w03, w23);
    not n6(w03, t);
    not n60(w23, g);
endmodule // blackbox

Lab1/blackbox_tb.v
module blackbox_test;
  reg n_in, u_in, r_in;
  wire o_out;
  blackbox box(o_out, n_in, u_in, r_in);

  initial begin

    $dumpfile("blackbox.vcd");
    $dumpvars(0,blackbox_test);

    n_in = 0; u_in = 0; r_in = 0; # 10;
    n_in = 0; u_in = 0; r_in = 1; # 10;
    n_in = 0; u_in = 1; r_in = 0; # 10;
    n_in = 0; u_in = 1; r_in = 1; # 10;
    n_in = 1; u_in = 0; r_in = 0; # 10;
    n_in = 1; u_in = 0; r_in = 1; # 10;
    n_in = 1; u_in = 1; r_in = 0; # 10;
    n_in = 1; u_in = 1; r_in = 1; # 10;

    $finish;

  end

  initial
      $monitor("At time %2t, n_in = %d u_in = %d r_in = %d, o_out = %d",
               $time, n_in, u_in, r_in, o_out);
endmodule // blackbox_test

Lab1/blackbox.vcd
$date
	Tue Aug 27 21:19:34 2019
$end
$version
	Icarus Verilog
$end
$timescale
	1s
$end
$scope module blackbox_test $end
$var wire 1 ! o_out $end
$var reg 1 " n_in $end
$var reg 1 # r_in $end
$var reg 1 $ u_in $end
$scope module box $end
$var wire 1 ! b $end
$var wire 1 " g $end
$var wire 1 $ r $end
$var wire 1 # t $end
$var wire 1 % w01 $end
$var wire 1 & w02 $end
$var wire 1 ' w03 $end
$var wire 1 ( w04 $end
$var wire 1 ) w11 $end
$var wire 1 * w23 $end
$var wire 1 + w28 $end
$var wire 1 , w35 $end
$var wire 1 - w44 $end
$var wire 1 . w45 $end
$var wire 1 / w55 $end
$var wire 1 0 w80 $end
$var wire 1 1 w81 $end
$var wire 1 2 w86 $end
$var wire 1 3 w88 $end
$var wire 1 4 w89 $end
$var wire 1 5 w92 $end
$var wire 1 6 w94 $end
$upscope $end
$upscope $end
$enddefinitions $end
#0
$dumpvars
06
05
04
13
12
01
10
1/
0.
1-
0,
0+
1*
1)
1(
1'
0&
1%
0$
0#
0"
0!
$end
#10
03
0%
15
11
0'
1#
#20
1!
1&
1+
1.
13
1(
1%
16
02
05
01
1'
0/
0-
0#
1$
#30
0!
0&
0+
0.
0%
04
06
11
0'
1#
#40
1!
1&
1+
1.
1%
1,
01
1'
1/
00
1-
12
0)
0*
0#
0$
1"
#50
03
15
0'
1#
#60
0&
0+
0!
0.
13
1(
0,
05
1'
0/
10
0-
0#
1$
#70
03
0%
15
11
0'
1#
