Lab4/decoder.v
// mips_decode: a decoder for MIPS arithmetic instructions
//
// alu_src2    (output) - should the 2nd ALU source be a register (0) or an immediate (1)
// rd_src      (output) - should the destination register be rd (0) or rt (1)
// writeenable (output) - should a new value be captured by the register file
// alu_op      (output) - control signal to be sent to the ALU
// except      (output) - set to 1 when the opcode/funct combination is unrecognized
// opcode      (input)  - the opcode field from the instruction
// funct       (input)  - the function field from the instruction
//

module mips_decode(alu_src2, rd_src, writeenable, alu_op, except, opcode, funct);
    output       alu_src2, rd_src, writeenable, except;
    output [2:0] alu_op;
    input  [5:0] opcode, funct;
    wire ADD, ADDI, SUB, AND, ANDI, OR, NOR, XOR, ORI, XORI;

    assign alu_src2 = opcode[0] | opcode[1] | opcode[2] | opcode[3] | opcode[4] | opcode[5];
    assign rd_src = alu_src2;

    assign ADD = (opcode == 6'h00) & (funct == `OP0_ADD);
    assign ADDI = opcode == `OP_ADDI;
    assign SUB = (opcode == 6'h00) & (funct == `OP0_SUB);
    assign AND = (opcode == 6'h00) & (funct == `OP0_AND);
    assign ANDI = opcode == `OP_ANDI;
    assign OR = (opcode == 6'h00) & (funct == `OP0_OR);
    assign NOR = (opcode == 6'h00) & (funct == `OP0_NOR);
    assign XOR = (opcode == 6'h00) & (funct == `OP0_XOR);
    assign ORI = opcode == `OP_ORI;
    assign XORI = opcode == `OP_XORI;

    assign alu_op = ADD | ADDI ? 2 :
            SUB ? 3 :
            AND | ANDI ? 4 :
            OR | ORI ? 5 :
            NOR ? 6 :
            XOR | XORI ? 7 :
            0;

    assign except = ~(ADD | ADDI | SUB | AND | ANDI | OR | ORI | NOR | XOR | XORI);
    assign writeenable = ~except;

endmodule // mips_decode

Lab4/decoder_tb.v
module decoder_test;
    reg [5:0] opcode, funct;

    initial begin
        $dumpfile("decoder.vcd");
        $dumpvars(0, decoder_test);

             opcode = `OP_OTHER0; funct = `OP0_ADD; // try addition
        # 10 opcode = `OP_OTHER0; funct = `OP0_SUB; // try subtraction
        // add more tests here!
        # 10 opcode = 6'h00; funct = `OP0_OR;
        # 10 opcode = 6'h00; funct = `OP0_AND;
        # 10 opcode = 6'h00; funct = `OP0_NOR;
        # 10 opcode = 6'h00; funct = `OP0_XOR;
        # 10 opcode = `OP_ORI;
        # 10 opcode = `OP_ADDI;
        # 10 opcode = `OP_XORI;
        # 10 opcode = `OP_ANDI;
        # 10 opcode = 6'h00; funct = 6'h01;
        # 10 $finish;
    end

    // use gtkwave to test correctness
    wire [2:0] alu_op;
    wire       alu_src2, rd_src, writeenable, except;
    mips_decode decoder(alu_src2, rd_src, writeenable, alu_op, except,
                        opcode, funct);
endmodule // decoder_test

Lab4/decoder.vcd
$date
	Tue Sep 17 19:09:03 2019
$end
$version
	Icarus Verilog
$end
$timescale
	1s
$end
$scope module decoder_test $end
$var wire 1 ! writeenable $end
$var wire 1 " rd_src $end
$var wire 1 # except $end
$var wire 1 $ alu_src2 $end
$var wire 3 % alu_op [2:0] $end
$var reg 6 & funct [5:0] $end
$var reg 6 ' opcode [5:0] $end
$scope module decoder $end
$var wire 1 ( ADD $end
$var wire 1 ) AND $end
$var wire 1 * NOR $end
$var wire 1 + OR $end
$var wire 1 , SUB $end
$var wire 1 - XOR $end
$var wire 1 $ alu_src2 $end
$var wire 1 # except $end
$var wire 6 . funct [5:0] $end
$var wire 6 / opcode [5:0] $end
$var wire 1 " rd_src $end
$var wire 1 ! writeenable $end
$var wire 3 0 alu_op [2:0] $end
$var wire 1 1 XORI $end
$var wire 1 2 ORI $end
$var wire 1 3 ANDI $end
$var wire 1 4 ADDI $end
$upscope $end
$upscope $end
$enddefinitions $end
#0
$dumpvars
04
03
02
01
b10 0
b0 /
b100000 .
0-
0,
0+
0*
0)
1(
b0 '
b100000 &
b10 %
0$
0#
0"
1!
$end
#10
b11 %
b11 0
0(
1,
b100010 &
b100010 .
#20
b101 %
b101 0
0,
1+
b100101 &
b100101 .
#30
1!
0#
b100 %
b100 0
1)
0+
b100100 &
b100100 .
#40
b110 %
b110 0
0)
1*
b100111 &
b100111 .
#50
b111 %
b111 0
0*
1-
b100110 &
b100110 .
#60
b101 %
b101 0
1"
1$
0-
12
b1101 '
b1101 /
#70
1!
0#
b10 %
b10 0
14
02
b1000 '
b1000 /
#80
b111 %
b111 0
04
11
b1110 '
b1110 /
#90
b100 %
b100 0
1!
0#
13
01
b1100 '
b1100 /
#100
0!
1#
0"
0$
b0 %
b0 0
b1 &
b1 .
03
b0 '
b0 /
