Lab5/decoder.v
// mips_decode: a decoder for MIPS arithmetic instructions
//
// alu_op       (output) - control signal to be sent to the ALU
// writeenable  (output) - should a new value be captured by the register file
// rd_src       (output) - should the destination register be rd (0) or rt (1)
// alu_src2     (output) - should the 2nd ALU source be a register (0) or an immediate (1)
// except       (output) - set to 1 when we don't recognize an opdcode & funct combination
// control_type (output) - 00 = fallthrough, 01 = branch_target, 10 = jump_target, 11 = jump_register
// mem_read     (output) - the register value written is coming from the memory
// word_we      (output) - we're writing a word's worth of data
// byte_we      (output) - we're only writing a byte's worth of data
// byte_load    (output) - we're doing a byte load
// slt          (output) - the instruction is an slt
// lui          (output) - the instruction is a lui
// addm         (output) - the instruction is an addm
// opcode        (input) - the opcode field from the instruction
// funct         (input) - the function field from the instruction
// zero          (input) - from the ALU
//

module mips_decode(alu_op, writeenable, rd_src, alu_src2, except, control_type,
                   mem_read, word_we, byte_we, byte_load, slt, lui, addm,
                   opcode, funct, zero);
    output [2:0] alu_op;
    output       writeenable, rd_src, alu_src2, except;
    output [1:0] control_type;
    output       mem_read, word_we, byte_we, byte_load, slt, lui, addm;
    input  [5:0] opcode, funct;
    input        zero;
    wire ADD, ADDI, SUB, AND, ANDI, OR, NOR, XOR, ORI, XORI, BNE, BEQ, J, JR, LUI, SLT, LW, LBU, SW, SB, ADDM;

    assign alu_src2 = (opcode[0] | opcode[1] | opcode[2] | opcode[3] | opcode[4] | opcode[5]) & ~BNE & ~BEQ;
    assign rd_src = alu_src2;

    assign ADD = (opcode == 6'h00) & (funct == `OP0_ADD);
    assign ADDI = opcode == `OP_ADDI;
    assign SUB = (opcode == 6'h00) & (funct == `OP0_SUB);
    assign AND = (opcode == 6'h00) & (funct == `OP0_AND);
    assign ANDI = opcode == `OP_ANDI;
    assign OR = (opcode == 6'h00) & (funct == `OP0_OR);
    assign NOR = (opcode == 6'h00) & (funct == `OP0_NOR);
    assign XOR = (opcode == 6'h00) & (funct == `OP0_XOR);
    assign ORI = opcode == `OP_ORI;
    assign XORI = opcode == `OP_XORI;

    assign BEQ = opcode == `OP_BEQ;
    assign BNE = opcode == `OP_BNE;
    assign J = opcode == `OP_J;
    assign JR = (opcode == 6'h00) & (funct == `OP0_JR);
    assign LUI = opcode == `OP_LUI;
    assign SLT = (opcode == 6'h00) & (funct == `OP0_SLT);
    assign LW = opcode == `OP_LW;
    assign LBU = opcode == `OP_LBU;
    assign SW = opcode == `OP_SW;
    assign SB = opcode == `OP_SB;
    assign ADDM = (opcode == 6'h00) & (funct == `OP0_ADDM);

    assign lui = LUI;
    assign slt = SLT;
    assign mem_read = LW | LBU;
    assign byte_load = LBU;
    assign word_we = SW;
    assign byte_we = SB;
    assign addm = ADDM;

    assign control_type[0] = (BNE & ~zero) | (BEQ & zero) | JR;
    assign control_type[1] = J | JR;

    assign alu_op = ADD | ADDI | ADDM ? 2 :
            SUB | BNE | BEQ | SLT ? 3 :
            AND | ANDI ? 4 :
            OR | ORI ? 5 :
            NOR ? 6 :
            XOR | XORI ? 7 :
            0;

    assign except = ~(ADD | ADDI | SUB | AND | ANDI | OR | ORI | NOR | XOR | XORI | BNE | BEQ | J | JR | LUI | SLT | LW | LBU | SW | SB | ADDM);
    assign writeenable = ~except & ~BNE & ~BEQ & ~J & ~JR & ~SW & ~SB;
endmodule // mips_decode

Lab5/decoder_tb.v
module decoder_test;
    reg [5:0] opcode, funct;
    reg       zero  = 0;

    initial begin
        $dumpfile("decoder.vcd");
        $dumpvars(0, decoder_test);

        // remember that all your instructions from last week should still work
             opcode = `OP_OTHER0; funct = `OP0_ADD; // see if addition still works
        # 10 opcode = `OP_OTHER0; funct = `OP0_SUB; // see if subtraction still works
        // test all of the others here
        # 10 opcode = `OP_J;
        # 10 opcode = `OP_SW;
        # 10 opcode = `OP_OTHER0; funct = `OP0_ADDM;
        # 10 opcode = `OP_OTHER0; funct = `OP0_JR;
        // as should all the new instructions from this week
        # 10 opcode = `OP_BEQ; zero = 0; // try a not taken beq
        # 10 opcode = `OP_BEQ; zero = 1; // try a taken beq
        // add more tests here!

        # 10 $finish;
    end

    // use gtkwave to test correctness
    wire [2:0] alu_op;
    wire       writeenable, rd_src, alu_src2, except;
    wire [1:0] control_type;
    wire       mem_read, word_we, byte_we, byte_load, slt, lui, addm;
    mips_decode decoder(alu_op, writeenable, rd_src, alu_src2, except, control_type,
                        mem_read, word_we, byte_we, byte_load, slt, lui, addm,
                        opcode, funct, zero);
endmodule // decoder_test

Lab5/decoder.vcd
$date
	Fri Sep 27 14:56:13 2019
$end
$version
	Icarus Verilog
$end
$timescale
	1s
$end
$scope module decoder_test $end
$var wire 1 ! writeenable $end
$var wire 1 " word_we $end
$var wire 1 # slt $end
$var wire 1 $ rd_src $end
$var wire 1 % mem_read $end
$var wire 1 & lui $end
$var wire 1 ' except $end
$var wire 2 ( control_type [1:0] $end
$var wire 1 ) byte_we $end
$var wire 1 * byte_load $end
$var wire 1 + alu_src2 $end
$var wire 3 , alu_op [2:0] $end
$var wire 1 - addm $end
$var reg 6 . funct [5:0] $end
$var reg 6 / opcode [5:0] $end
$var reg 1 0 zero $end
$scope module decoder $end
$var wire 1 1 ADD $end
$var wire 1 2 ADDM $end
$var wire 1 3 AND $end
$var wire 1 4 JR $end
$var wire 1 5 NOR $end
$var wire 1 6 OR $end
$var wire 1 7 SLT $end
$var wire 1 8 SUB $end
$var wire 1 9 XOR $end
$var wire 1 - addm $end
$var wire 1 + alu_src2 $end
$var wire 1 * byte_load $end
$var wire 1 ) byte_we $end
$var wire 1 ' except $end
$var wire 6 : funct [5:0] $end
$var wire 1 & lui $end
$var wire 1 % mem_read $end
$var wire 6 ; opcode [5:0] $end
$var wire 1 $ rd_src $end
$var wire 1 # slt $end
$var wire 1 " word_we $end
$var wire 1 ! writeenable $end
$var wire 1 0 zero $end
$var wire 2 < control_type [1:0] $end
$var wire 3 = alu_op [2:0] $end
$var wire 1 > XORI $end
$var wire 1 ? SW $end
$var wire 1 @ SB $end
$var wire 1 A ORI $end
$var wire 1 B LW $end
$var wire 1 C LUI $end
$var wire 1 D LBU $end
$var wire 1 E J $end
$var wire 1 F BNE $end
$var wire 1 G BEQ $end
$var wire 1 H ANDI $end
$var wire 1 I ADDI $end
$upscope $end
$upscope $end
$enddefinitions $end
#0
$dumpvars
0I
0H
0G
0F
0E
0D
0C
0B
0A
0@
0?
0>
b10 =
b0 <
b0 ;
b100000 :
09
08
07
06
05
04
03
02
11
00
b0 /
b100000 .
0-
b10 ,
0+
0*
0)
b0 (
0'
0&
0%
0$
0#
0"
1!
$end
#10
b11 ,
b11 =
01
18
b100010 .
b100010 :
#20
1$
1+
b0 ,
b0 =
0!
08
b10 (
b10 <
1E
b10 /
b10 ;
#30
b0 (
b0 <
0E
1"
1?
b101011 /
b101011 ;
#40
0$
0+
b10 ,
b10 =
1!
1-
12
b101100 .
b101100 :
0"
0?
b0 /
b0 ;
#50
0!
b0 ,
b0 =
0'
b11 (
b11 <
14
0-
02
b1000 .
b1000 :
#60
0'
b11 ,
b11 =
0!
b0 (
b0 <
04
1G
b100 /
b100 ;
#70
b1 (
b1 <
10
